xutk/__init__.py
xutk/log.py
xutk/mp_runner.py
xutk/perf.py
xutk/verchk.py
xutk-0.3.4.dist-info/METADATA
xutk-0.3.4.dist-info/WHEEL
xutk-0.3.4.dist-info/top_level.txt
xutk-0.3.4.dist-info/RECORD
