Metadata-Version: 2.4
Name: xutk
Version: 0.3.4
Summary: Xulab toolkit in python
Requires-Python: <3.15,>=3.11
Requires-Dist: colorama>=0.4.6
Requires-Dist: psutil>=7.1.0
